{
  "OSHINOKO_MONSTER_HOSHINO_AI.moves.PHASE1_DRAW.title": "First Meeting",
  "OSHINOKO_MONSTER_HOSHINO_AI.moves.PHASE1_ENERGY.title": "Blessing of Energy",
  "OSHINOKO_MONSTER_HOSHINO_AI.moves.PHASE1_OPENING.title": "Idol Entrance",
  "OSHINOKO_MONSTER_HOSHINO_AI.moves.PHASE2_ORBIT.title": "Starlit Orbit",
  "OSHINOKO_MONSTER_HOSHINO_AI.moves.PHASE2_STATS.title": "Idol Cheer",
  "OSHINOKO_MONSTER_HOSHINO_AI.moves.PHASE3_NODRAW.title": "Glance Around",
  "OSHINOKO_MONSTER_HOSHINO_AI.moves.PHASE3_REBIRTH_CARD.title": "Rebirth",
  "OSHINOKO_MONSTER_HOSHINO_AI.name": "Hoshino Ai",
  "OSHINOKO_MONSTER_KAMIKI_HIKARU.moves.KAMIKI_PHASE_TRANSITION.title": "Truth Revealed",
  "OSHINOKO_MONSTER_KAMIKI_HIKARU.moves.P1_ATTACK.title": "Dark Strike",
  "OSHINOKO_MONSTER_KAMIKI_HIKARU.moves.P1_ATTACK_ESCAPE.title": "Escape Strike",
  "OSHINOKO_MONSTER_KAMIKI_HIKARU.moves.P1_ATTACK_FOG.title": "Mist Strike",
  "OSHINOKO_MONSTER_KAMIKI_HIKARU.moves.P1_ATTACK_SOULBIND.title": "Soulbind Strike",
  "OSHINOKO_MONSTER_KAMIKI_HIKARU.moves.P1_INTERRUPTED.title": "Interrupted",
  "OSHINOKO_MONSTER_KAMIKI_HIKARU.moves.P2_ATTACK.title": "Ruinous Strike",
  "OSHINOKO_MONSTER_KAMIKI_HIKARU.moves.P2_ATTACK_GAIN_REVENGE.title": "Vengeful Strike",
  "OSHINOKO_MONSTER_KAMIKI_HIKARU.moves.P2_ATTACK_TRAP.title": "Trap Strike",
  "OSHINOKO_MONSTER_KAMIKI_HIKARU.moves.P2_ATTACK_VULNERABLE.title": "Exposing Strike",
  "OSHINOKO_MONSTER_KAMIKI_HIKARU.moves.P2_ATTACK_WEAK_FRAIL.title": "Withering Strike",
  "OSHINOKO_MONSTER_KAMIKI_HIKARU.name": "Kamiki Hikaru"
}
